gradio_tools/__init__.py
gradio_tools/tools/__init__.py
gradio_tools/tools/bark.py
gradio_tools/tools/clip_interrogator.py
gradio_tools/tools/document_qa.py
gradio_tools/tools/gradio_tool.py
gradio_tools/tools/image_captioning.py
gradio_tools/tools/image_to_music.py
gradio_tools/tools/prompt_generator.py
gradio_tools/tools/sam_with_clip.py
gradio_tools/tools/stable_diffusion.py
gradio_tools/tools/text_to_video.py
gradio_tools/tools/whisper.py
gradio_tools-0.0.9.dist-info/METADATA
gradio_tools-0.0.9.dist-info/WHEEL
gradio_tools-0.0.9.dist-info/licenses/LICENSE
gradio_tools-0.0.9.dist-info/RECORD
