Metadata-Version: 2.1
Name: gradio_tools
Version: 0.0.9
Summary: Use Gradio Apps as tools for LLM Agents
Author-email: Freddy Boulton <alfonsoboulton@gmail.com>
License-Expression: MIT
License-File: LICENSE
Classifier: Development Status :: 4 - Beta
Classifier: Intended Audience :: Developers
Classifier: Intended Audience :: Information Technology
Classifier: Intended Audience :: System Administrators
Classifier: License :: OSI Approved :: MIT License
Classifier: Operating System :: OS Independent
Classifier: Programming Language :: Python
Classifier: Programming Language :: Python :: 3 :: Only
Classifier: Programming Language :: Python :: 3.8
Classifier: Programming Language :: Python :: 3.9
Classifier: Programming Language :: Python :: 3.10
Classifier: Programming Language :: Python :: 3.11
Classifier: Topic :: Internet
Classifier: Topic :: Software Development
Classifier: Topic :: Software Development :: Libraries
Classifier: Topic :: Software Development :: Libraries :: Application Frameworks
Classifier: Topic :: Software Development :: Libraries :: Python Modules
Classifier: Typing :: Typed
Requires-Python: >=3.8
Requires-Dist: gradio-client>=0.1.2
Provides-Extra: all
Requires-Dist: gradio-tools[langchain]; extra == 'all'
Requires-Dist: gradio-tools[minichain]; extra == 'all'
Provides-Extra: dev
Requires-Dist: gradio-tools[all]; extra == 'dev'
Requires-Dist: gradio-tools[test]; extra == 'dev'
Provides-Extra: langchain
Requires-Dist: langchain; extra == 'langchain'
Requires-Dist: openai; extra == 'langchain'
Provides-Extra: minichain
Requires-Dist: gradio; extra == 'minichain'
Requires-Dist: minichain>=0.3.3; extra == 'minichain'
Provides-Extra: test
Requires-Dist: black==22.6.0; extra == 'test'
Requires-Dist: isort<6.0.0,>=5.0.6; extra == 'test'
Requires-Dist: pyright==1.1.298; extra == 'test'
Requires-Dist: pytest; extra == 'test'
Requires-Dist: ruff==0.0.260; extra == 'test'
